voodoo/__init__.py
voodoo/hook.py
voodoo/main.py
voodoo/locomotive/__init__.py
voodoo/locomotive/docker-compose.yml
voodoo/locomotive/hook.py
voodoo/odoo/__init__.py
voodoo/odoo/docker-compose.yml
voodoo/odoo/hook.py
voodoo/rails/__init__.py
voodoo/rails/docker-compose.yml
voodoo/rails/hook.py
voodoo/ruby/__init__.py
voodoo/ruby/hook.py
voodoo/wagon/__init__.py
voodoo/wagon/docker-compose.yml
voodoo/wagon/hook.py
voodoo_cli-2.6.8.dist-info/DESCRIPTION.rst
voodoo_cli-2.6.8.dist-info/METADATA
voodoo_cli-2.6.8.dist-info/RECORD
voodoo_cli-2.6.8.dist-info/WHEEL
voodoo_cli-2.6.8.dist-info/entry_points.txt
voodoo_cli-2.6.8.dist-info/metadata.json
voodoo_cli-2.6.8.dist-info/top_level.txt
