Metadata-Version: 2.0
Name: voodoo-cli
Version: 2.6.8
Summary: Environment builder for Odoo
Home-page: https://github.com/akretion/voodoo/
Author: Akretion
Author-email: contact@akretion.com
License: AGPLv3+
Platform: UNKNOWN
Requires-Dist: docker-compose (>=1.13)
Requires-Dist: plumbum
Requires-Dist: rainbow-logging-handler
Requires-Dist: unidecode
